post_train/__init__.py
post_train/foo.py
post_train-0.0.2a0.dist-info/LICENSE
post_train-0.0.2a0.dist-info/METADATA
post_train-0.0.2a0.dist-info/WHEEL
post_train-0.0.2a0.dist-info/RECORD
