Metadata-Version: 2.1
Name: post-train
Version: 0.0.2a0
Summary: Post-training framework
Home-page: https://github.com/nlile/post-train
Author: nlile
Author-email: n@synthlabs.ai
Requires-Python: >=3.8,<4.0
Classifier: Programming Language :: Python :: 3
Classifier: Programming Language :: Python :: 3.8
Classifier: Programming Language :: Python :: 3.9
Classifier: Programming Language :: Python :: 3.10
Classifier: Programming Language :: Python :: 3.11
Classifier: Programming Language :: Python :: 3.12
Project-URL: Documentation, https://nlile.github.io/post-train/
Project-URL: Repository, https://github.com/nlile/post-train
